vstolib/__init__.py
vstolib/annotator.py
vstolib/constants.py
vstolib/default.py
vstolib/gencode.py
vstolib/index.py
vstolib/intersect.py
vstolib/logging.py
vstolib/main.py
vstolib/overlap.py
vstolib/position_annotation.py
vstolib/utilities.py
vstolib/cli/__init__.py
vstolib/cli/cli_annotate.py
vstolib/cli/cli_diff.py
vstolib/cli/cli_intersect.py
vstolib/cli/cli_main.py
vstolib/cli/cli_merge.py
vstolib/cli/cli_overlap.py
vstolib/cli/cli_vcf2tsv.py
vstolib/vcf/__init__.py
vstolib/vcf/clairs.py
vstolib/vcf/common.py
vstolib/vcf/cutesv.py
vstolib/vcf/dbsnp.py
vstolib/vcf/deepvariant.py
vstolib/vcf/delly2.py
vstolib/vcf/gatk4_mutect2.py
vstolib/vcf/lumpy.py
vstolib/vcf/manta.py
vstolib/vcf/pbsv.py
vstolib/vcf/savana.py
vstolib/vcf/severus.py
vstolib/vcf/sniffles2.py
vstolib/vcf/strelka2.py
vstolib/vcf/svim.py
vstolib/vcf/svisionpro.py
vstol-0.4.1.dist-info/METADATA
vstol-0.4.1.dist-info/WHEEL
vstol-0.4.1.dist-info/entry_points.txt
vstol-0.4.1.dist-info/top_level.txt
vstol-0.4.1.dist-info/RECORD
