Metadata-Version: 2.1
Name: vstol
Version: 0.4.1
Project-URL: Homepage, https://github.com/pirl-unc/vstol
Project-URL: Bug Tracker, https://github.com/pirl-unc/vstol
Keywords: cancer,dna,occam's variant grammar,small variants,somatic variants,structural variants,tumor,variant standardization,variant toolkit,vcf
Classifier: Programming Language :: Rust
Classifier: Programming Language :: Python :: Implementation :: CPython
Classifier: Programming Language :: Python :: Implementation :: PyPy
Requires-Python: >=3.10
